netrange/__init__.py
netrange/__main__.py
netrange/_parser.py
netrange/_utilities.py
netrange/cli.py
netrange/dump.py
netrange/exceptions.py
netrange/load.py
netrange-0.0.19.dist-info/LICENSE
netrange-0.0.19.dist-info/METADATA
netrange-0.0.19.dist-info/WHEEL
netrange-0.0.19.dist-info/entry_points.txt
netrange-0.0.19.dist-info/top_level.txt
netrange-0.0.19.dist-info/RECORD
