Metadata-Version: 2.1
Name: netrange
Version: 0.0.19
Summary: A simple package for reading and ranging IPs and ports.
Home-page: https://github.com/muhannadengineer/netrange
Author: Muhannad Alghamdi
Author-email: muhannadengineer@gmail.com
License: MIT
Keywords: ip address port range
Platform: UNKNOWN
Classifier: License :: OSI Approved :: MIT License
Classifier: Programming Language :: Python :: 3.7
Classifier: Programming Language :: Python :: 3.6
Classifier: Operating System :: OS Independent
